dnarecords/__init__.py
dnarecords/helper.py
dnarecords/macros.py
dnarecords/reader.py
dnarecords/writer.py
dnarecords-0.2.7.dist-info/LICENSE
dnarecords-0.2.7.dist-info/WHEEL
dnarecords-0.2.7.dist-info/METADATA
dnarecords-0.2.7.dist-info/RECORD
