Metadata-Version: 2.1
Name: dnarecords
Version: 0.2.7
Summary: Genomics data ML ready
License: MIT
Keywords: DNA,Deep Learning
Author: Atray Dixit, Andrés Mañas Mañas, Lucas Seninge
Requires-Python: >=3.7.1,<3.11
Classifier: License :: OSI Approved :: MIT License
Classifier: Programming Language :: Python :: 3
Classifier: Programming Language :: Python :: 3.10
Classifier: Programming Language :: Python :: 3.8
Classifier: Programming Language :: Python :: 3.9
Requires-Dist: fastparquet (>=0.8.1,<0.9.0)
Requires-Dist: hail (>=0.2.94,<0.3.0)
Requires-Dist: pyarrow (>=8.0.0,<9.0.0)
Requires-Dist: tensorflow (>=2.6.0,<3.0.0)
